nornir_scrapli/__init__.py
nornir_scrapli/connection.py
nornir_scrapli/exceptions.py
nornir_scrapli/helper.py
nornir_scrapli/py.typed
nornir_scrapli/result.py
nornir_scrapli/functions/__init__.py
nornir_scrapli/functions/print_structured_result.py
nornir_scrapli/tasks/__init__.py
nornir_scrapli/tasks/cfg/__init__.py
nornir_scrapli/tasks/cfg/abort_config.py
nornir_scrapli/tasks/cfg/commit_config.py
nornir_scrapli/tasks/cfg/diff_config.py
nornir_scrapli/tasks/cfg/get_config.py
nornir_scrapli/tasks/cfg/get_version.py
nornir_scrapli/tasks/cfg/load_config.py
nornir_scrapli/tasks/core/__init__.py
nornir_scrapli/tasks/core/get_prompt.py
nornir_scrapli/tasks/core/send_command.py
nornir_scrapli/tasks/core/send_commands.py
nornir_scrapli/tasks/core/send_commands_from_file.py
nornir_scrapli/tasks/core/send_config.py
nornir_scrapli/tasks/core/send_configs.py
nornir_scrapli/tasks/core/send_configs_from_file.py
nornir_scrapli/tasks/core/send_interactive.py
nornir_scrapli/tasks/netconf/__init__.py
nornir_scrapli/tasks/netconf/capabilities.py
nornir_scrapli/tasks/netconf/commit.py
nornir_scrapli/tasks/netconf/delete_config.py
nornir_scrapli/tasks/netconf/discard.py
nornir_scrapli/tasks/netconf/edit_config.py
nornir_scrapli/tasks/netconf/get.py
nornir_scrapli/tasks/netconf/get_config.py
nornir_scrapli/tasks/netconf/lock.py
nornir_scrapli/tasks/netconf/rpc.py
nornir_scrapli/tasks/netconf/unlock.py
nornir_scrapli/tasks/netconf/validate.py
nornir_scrapli-2025.1.30.dist-info/LICENSE
nornir_scrapli-2025.1.30.dist-info/METADATA
nornir_scrapli-2025.1.30.dist-info/WHEEL
nornir_scrapli-2025.1.30.dist-info/entry_points.txt
nornir_scrapli-2025.1.30.dist-info/top_level.txt
nornir_scrapli-2025.1.30.dist-info/RECORD
