Metadata-Version: 2.2
Name: nornir_scrapli
Version: 2025.1.30
Summary: Scrapli's plugin for Nornir
Author-email: Carl Montanari <carl.r.montanari@gmail.com>
License: MIT License
Project-URL: Homepage, https://github.com/scrapli/nornir_scrapli
Project-URL: Docs, https://scrapli.github.io/nornir_scrapli/
Keywords: arista,automation,cisco,eos,iosxe,iosxr,juniper,junos,netconf,network,nxos,ssh,telnet
Classifier: License :: OSI Approved :: MIT License
Classifier: Operating System :: POSIX :: Linux
Classifier: Operating System :: MacOS
Classifier: Programming Language :: Python
Classifier: Programming Language :: Python :: 3.9
Classifier: Programming Language :: Python :: 3.10
Classifier: Programming Language :: Python :: 3.11
Classifier: Programming Language :: Python :: 3.12
Classifier: Programming Language :: Python :: 3.13
Classifier: Programming Language :: Python :: 3 :: Only
Classifier: Topic :: Software Development :: Libraries :: Python Modules
Requires-Python: >=3.9
License-File: LICENSE
Requires-Dist: nornir>=3.0.0
Requires-Dist: nornir_utils>=0.1.0
Requires-Dist: ntc_templates>=1.1.0
Requires-Dist: scrapli>=2022.01.30
Requires-Dist: scrapli_cfg>=2022.01.30
Requires-Dist: scrapli_community>=2021.01.30
Requires-Dist: scrapli_netconf>=2022.01.30
Requires-Dist: textfsm>=1.1.0
Provides-Extra: dev
Requires-Dist: black<25.0.0,>=23.3.0; extra == "dev"
Requires-Dist: darglint<2.0.0,>=1.8.1; extra == "dev"
Requires-Dist: isort<6.0.0,>=5.10.1; extra == "dev"
Requires-Dist: mypy<2.0.0,>1.0.0; extra == "dev"
Requires-Dist: nox==2024.4.15; extra == "dev"
Requires-Dist: pydocstyle<7.0.0,>=6.1.1; extra == "dev"
Requires-Dist: pylint<4.0.0,>=3.0.0; extra == "dev"
Requires-Dist: pytest-cov<5.0.0,>=3.0.0; extra == "dev"
Requires-Dist: pytest<8.0.0,>=7.0.0; extra == "dev"
Requires-Dist: toml<1.0.0,>=0.10.2; extra == "dev"
Requires-Dist: genie>=20.2; (sys_platform != "win32" and python_version < "3.13") and extra == "dev"
Requires-Dist: pyats>=20.2; (sys_platform != "win32" and python_version < "3.13") and extra == "dev"
Provides-Extra: docs
Requires-Dist: mdx-gh-links<1.0,>=0.2; extra == "docs"
Requires-Dist: mkdocs<2.0.0,>=1.2.3; extra == "docs"
Requires-Dist: mkdocs-gen-files<1.0.0,>=0.4.0; extra == "docs"
Requires-Dist: mkdocs-literate-nav<1.0.0,>=0.5.0; extra == "docs"
Requires-Dist: mkdocs-material<10.0.0,>=8.1.6; extra == "docs"
Requires-Dist: mkdocs-material-extensions<2.0.0,>=1.0.3; extra == "docs"
Requires-Dist: mkdocs-section-index<1.0.0,>=0.3.4; extra == "docs"
Requires-Dist: mkdocstrings[python]<1.0.0,>=0.19.0; extra == "docs"
Provides-Extra: genie
Requires-Dist: genie>=20.2; (sys_platform != "win32" and python_version < "3.13") and extra == "genie"
Requires-Dist: pyats>=20.2; (sys_platform != "win32" and python_version < "3.13") and extra == "genie"
